Metadata-Version: 2.1
Name: iyzipy
Version: 0.0.1
Summary: Iyzico Python Client
Home-page: https://gitlab.com/kalaomer/iyzipy
Author: kalaomer
Author-email: kalaomer@hotmail.com
License: MIT
Keywords: iyzico client payment
Platform: UNKNOWN
Classifier: Development Status :: 3 - Alpha
Classifier: Intended Audience :: Developers
Classifier: Topic :: Software Development :: Build Tools
Classifier: Programming Language :: Python :: 3
Classifier: Programming Language :: Python :: 3.3
Classifier: Programming Language :: Python :: 3.4
Classifier: Programming Language :: Python :: 3.5
Provides-Extra: test
